dlt_utils/__init__.py
dlt_utils/args.py
dlt_utils/azure_keyvault.py
dlt_utils/dates.py
dlt_utils/incremental.py
dlt_utils/logging.py
dlt_utils/pipeline.py
dlt_utils/schema.py
dlt_utils-0.5.1.dist-info/METADATA
dlt_utils-0.5.1.dist-info/WHEEL
dlt_utils-0.5.1.dist-info/top_level.txt
dlt_utils-0.5.1.dist-info/RECORD
