Metadata-Version: 2.4
Name: dlt_utils
Version: 0.5.1
Summary: Shared utilities for dlt data pipelines with multi-company support
Author: Jay van den Bos
License: MIT
Project-URL: Homepage, https://pypi.org/project/dlt_utils/
Project-URL: Repository, https://dev.azure.com/your-org/your-project/_git/dlt_utils
Keywords: dlt,data,pipeline,etl,incremental
Classifier: Development Status :: 4 - Beta
Classifier: Intended Audience :: Developers
Classifier: License :: OSI Approved :: MIT License
Classifier: Programming Language :: Python :: 3
Classifier: Programming Language :: Python :: 3.13
Classifier: Programming Language :: Python :: 3.14
Classifier: Topic :: Database
Classifier: Topic :: Software Development :: Libraries :: Python Modules
Requires-Python: >=3.13
Requires-Dist: dlt>=1.19.1
Requires-Dist: azure-identity>=1.15.0
Requires-Dist: azure-keyvault-secrets>=4.8.0
Provides-Extra: dev
Requires-Dist: pytest>=7.0; extra == "dev"
Requires-Dist: pytest-cov; extra == "dev"
Requires-Dist: ruff; extra == "dev"
